MANIFEST.in
README.md
setup.cfg
setup.py
docs/README.rst
quickavro/__init__.py
quickavro/__main__.py
quickavro/_compat.py
quickavro/constants.py
quickavro/encoder.py
quickavro/errors.py
quickavro/reader.py
quickavro/utils.py
quickavro/writer.py
quickavro.egg-info/PKG-INFO
quickavro.egg-info/SOURCES.txt
quickavro.egg-info/dependency_links.txt
quickavro.egg-info/entry_points.txt
quickavro.egg-info/not-zip-safe
quickavro.egg-info/top_level.txt
src/compat.h
src/convert.c
src/convert.h
src/encoderobject.c
src/encoderobject.h
src/module.c
src/quickavro.h
src/snappyobject.c
src/snappyobject.h